{
  "quotes": [
    {
      "text": "Life is about making an impact, not an income.",
      "source": "Kevin Kruse"
    },
    {
      "text": "Whatever the mind of a man can conceive and believe, it can achieve.",
      "source": "Napoleon Hill"
    },
    {
      "text": "Strive not to be a success, but rather to be a value.",
      "source": "Albert Einstein"
    },
    {
      "text": "You miss 100% of the shots you don't take.",
      "source": "Wayne Gretzky"
    },
    {
      "text": "We become what we think about.",
      "source": "Earl Nightingale"
    },
    {
      "text": "The most difficult thing is the decision to act, the rest is merely tenacity.",
      "source": "Amelia Earhart"
    },
    {
      "text": "Life is 10% what happens to me and 90% of how I react to it.",
      "source": "Charles Swindoll"
    },
    {
      "text": "Definiteness of purpose is the starting point of all achievement.",
      "source": "W. Clement Stone"
    },
  ]
}
